LICENSE
MANIFEST.in
README.rst
setup.cfg
setup.py
solstice/__init__.py
solstice/tools/__init__.py
solstice/tools/outliner/__init__.py
solstice/tools/outliner/__logging__.ini
solstice/tools/outliner/__version__.py
solstice/tools/outliner/core/__init__.py
solstice/tools/outliner/core/outliner.py
solstice/tools/outliner/outliners/__init__.py
solstice/tools/outliner/outliners/camera.py
solstice/tools/outliner/outliners/character.py
solstice/tools/outliner/outliners/fx.py
solstice/tools/outliner/outliners/light.py
solstice/tools/outliner/outliners/prop.py
solstice/tools/outliner/resources/icons/color/alembic.png
solstice/tools/outliner/resources/icons/color/alembic_black.png
solstice/tools/outliner/resources/icons/color/cameras.png
solstice/tools/outliner/resources/icons/color/characters.png
solstice/tools/outliner/resources/icons/color/fx.png
solstice/tools/outliner/resources/icons/color/lights.png
solstice/tools/outliner/resources/icons/color/props.png
solstice/tools/outliner/widgets/__init__.py
solstice/tools/outliner/widgets/outliner.py
solstice_tools_outliner.egg-info/PKG-INFO
solstice_tools_outliner.egg-info/SOURCES.txt
solstice_tools_outliner.egg-info/dependency_links.txt
solstice_tools_outliner.egg-info/not-zip-safe
solstice_tools_outliner.egg-info/requires.txt
solstice_tools_outliner.egg-info/top_level.txt